<?xml version="1.0" encoding="UTF-8"?>
<databaseChangeLog 
	xmlns="http://www.liquibase.org/xml/ns/dbchangelog" 
	logicalFilePath="db.changelog-v25.1.xml"
	xmlns:ext="http://www.liquibase.org/xml/ns/dbchangelog-ext" 
	xmlns:xsi="http://www.w3.org/2001/XMLSchema-instance" 
	xsi:schemaLocation="http://www.liquibase.org/xml/ns/dbchangelog http://www.liquibase.org/xml/ns/dbchangelog/dbchangelog-3.2.xsd http://www.liquibase.org/xml/ns/dbchangelog-ext http://www.liquibase.org/xml/ns/dbchangelog/dbchangelog-ext.xsd">
    <changeSet author="ilya (generated)" id="1446667770140-4">
        <addColumn tableName="worker">
            <column name="last_login" type="timestamp"/>
        </addColumn>
        <addColumn tableName="worker">
            <column name="last_logout" type="timestamp"/>
        </addColumn>
        <addColumn tableName="worker">
            <column name="last_che_persistent_id" type="UUID"/>
        </addColumn>
    </changeSet>
</databaseChangeLog>